vcfkit/__init__.py
vcfkit/annotate.py
vcfkit/calc.py
vcfkit/call.py
vcfkit/filter.py
vcfkit/geno.py
vcfkit/genome.py
vcfkit/hmm.py
vcfkit/phylo.py
vcfkit/primer.py
vcfkit/rename.py
vcfkit/stat.py
vcfkit/tajima.py
vcfkit/vcf2sql.py
vcfkit/vcf2tsv.py
vcfkit/vk.py
vcfkit/static/jquery-1.11.3.min.js
vcfkit/static/tree.html
vcfkit/static/jsphylosvg-1.55/jsphylosvg-min.js
vcfkit/static/jsphylosvg-1.55/jsphylosvg.js
vcfkit/static/jsphylosvg-1.55/raphael-min.js
vcfkit/static/jsphylosvg-1.55/readme.txt
vcfkit/static/primer3_config/dangle.dh
vcfkit/static/primer3_config/dangle.ds
vcfkit/static/primer3_config/loops.dh
vcfkit/static/primer3_config/loops.ds
vcfkit/static/primer3_config/primer3.license.txt
vcfkit/static/primer3_config/stack.dh
vcfkit/static/primer3_config/stack.ds
vcfkit/static/primer3_config/stackmm.dh
vcfkit/static/primer3_config/stackmm.ds
vcfkit/static/primer3_config/tetraloop.dh
vcfkit/static/primer3_config/tetraloop.ds
vcfkit/static/primer3_config/triloop.dh
vcfkit/static/primer3_config/triloop.ds
vcfkit/static/primer3_config/tstack.dh
vcfkit/static/primer3_config/tstack2.dh
vcfkit/static/primer3_config/tstack2.ds
vcfkit/static/primer3_config/tstack_tm_inf.ds
vcfkit/utils/__init__.py
vcfkit/utils/blastn.py
vcfkit/utils/fasta.py
vcfkit/utils/matrix.py
vcfkit/utils/primer3.py
vcfkit/utils/primer_vcf.py
vcfkit/utils/reference.py
vcfkit/utils/vcf.py
VCF_kit-0.2.9.dist-info/LICENSE
VCF_kit-0.2.9.dist-info/METADATA
VCF_kit-0.2.9.dist-info/WHEEL
VCF_kit-0.2.9.dist-info/entry_points.txt
VCF_kit-0.2.9.dist-info/top_level.txt
VCF_kit-0.2.9.dist-info/RECORD
